{"id":"KCTK","name":"Ingersoll","lat":40.56908,"lon":-90.07483,"elev":684.0,"mv":-2.0,"rw":[["RW09",40.57065,-90.08174,91.0,3294.0],["RW18",40.57308,-90.07387,183.0,3899.0],["RW27",40.57071,-90.06988,271.0,3294.0],["RW36",40.56237,-90.07416,3.0,3899.0]],"procs":[{"id":"R18","type":"APP","trans":[{"t":"LUYIL","k":"transition","legs":[["LUYIL",40.78149,-90.06823,"HF","R","+",2500,null,null,183.2,4.0,null,0,null,null,null,null]]},{"t":"PIA","k":"transition","legs":[["PIA",40.68007,-89.79275,"IF",null,null,null,null,null,null,null,null,0,null,null,null,null],["TULYU",40.77861,-89.89275,"TF",null,"+",2500,null,null,null,null,null,0,null,null,null,null],["LUYIL",40.78149,-90.06823,"TF",null,"+",2500,null,null,null,null,null,0,null,null,null,null]]},{"t":"VICKS","k":"transition","legs":[["VICKS",40.97129,-90.17379,"IF",null,null,null,null,null,null,null,null,0,null,null,null,null],["VICGU",40.84153,-90.17664,"TF",null,"+",2500,null,null,null,null,null,0,null,null,null,null],["LUYIL",40.78149,-90.06823,"TF",null,"+",2500,null,null,null,null,null,0,null,null,null,null]]},{"t":"(final)","k":"final","legs":[["LUYIL",40.78149,-90.06823,"IF",null,"+",2500,null,null,null,null,null,0,null,null,null,null],["NUVCI",40.66617,-90.07135,"TF",null,"+",2500,null,null,null,null,null,0,null,null,null,[40.57308,-90.07387]],["RW18",40.57308,-90.07387,"TF",null,null,722,null,null,null,null,-3.0,2,null,null,null,null],[null,null,null,"CA",null,"+",995,null,null,183.2,null,null,1,null,null,null,null],["CETRU",40.3534,-90.07979,"DF",null,"+",2500,null,null,null,null,null,2,null,null,null,null],["CETRU",40.3534,-90.07979,"HM","R","+",2500,null,null,3.2,4.0,null,0,null,null,null,null]]}],"name":"RNAV (GPS) RWY 18"},{"id":"R36","type":"APP","trans":[{"t":"BRL","k":"transition","legs":[["BRL",40.72346,-90.92589,"IF",null,null,null,null,null,null,null,null,0,null,null,null,null],["CANUT",40.3557,-90.23237,"TF",null,"+",2500,null,null,null,null,null,0,null,null,null,null],["CETRU",40.3534,-90.07979,"TF",null,"+",2500,null,null,null,null,null,0,null,null,null,null]]},{"t":"CETRU","k":"transition","legs":[["CETRU",40.3534,-90.07979,"HF","R","+",2500,null,null,3.2,4.0,null,0,null,null,null,null]]},{"t":"PIA","k":"transition","legs":[["PIA",40.68007,-89.79275,"IF",null,null,null,null,null,null,null,null,0,null,null,null,null],["LOPIY",40.34976,-89.86184,"TF",null,"+",2500,null,null,null,null,null,0,null,null,null,null],["CETRU",40.3534,-90.07979,"TF",null,"+",2500,null,null,null,null,null,0,null,null,null,null]]},{"t":"(final)","k":"final","legs":[["CETRU",40.3534,-90.07979,"IF",null,"+",2500,null,null,null,null,null,0,null,null,null,null],["JITID",40.46867,-90.07669,"TF",null,"+",2500,null,null,null,null,null,0,null,null,null,[40.56237,-90.07416]],["RW36",40.56237,-90.07416,"TF",null,null,710,null,null,null,null,-3.0,2,null,null,null,null],[null,null,null,"CA",null,"+",976,null,null,3.2,null,null,1,null,null,null,null],["LUYIL",40.78149,-90.06823,"DF",null,"+",2500,null,null,null,null,null,2,null,null,null,null],["LUYIL",40.78149,-90.06823,"HM","R","+",2500,null,null,183.2,4.0,null,0,null,null,null,null]]}],"name":"RNAV (GPS) RWY 36"},{"id":"VOR-A","type":"APP","trans":[{"t":"PIA","k":"transition","legs":[["PIA",40.68007,-89.79275,"HF","R","+",2300,null,null,238.8,null,null,0,["PIA",40.68007,-89.79275],0.0,0.0,null]]},{"t":"(final)","k":"final","legs":[["PIA",40.68007,-89.79275,"IF",null,"+",2300,null,null,null,null,null,0,["PIA",40.68007,-89.79275],0.0,0.0,null],["BRUNE",40.61136,-89.96801,"CF",null,"+",2300,null,null,238.8,9.0,null,0,["PIA",40.68007,-89.79275],238.8,9.0,[40.68007,-89.79275]],["MAHET",40.57113,-90.07011,"CF",null,null,684,null,null,238.8,5.3,0.0,2,["PIA",40.68007,-89.79275],238.8,14.3,null],[null,null,null,"CA",null,"+",1084,null,null,238.8,null,null,1,null,null,null,null],["PIA",40.68007,-89.79275,"DF","L","+",2300,null,null,null,null,null,2,null,null,null,null],["PIA",40.68007,-89.79275,"HM","R","+",2300,null,null,238.8,null,null,0,null,null,null,null]]}],"name":"VOR-A"}]}