{"id":"KDCM","name":"Chester Catawba Rgnl","lat":34.78933,"lon":-81.19578,"elev":657.0,"mv":-6.0,"rw":[["RW05",34.78592,-81.19708,61.0,4998.0],["RW17",34.79696,-81.20039,174.0,5000.0],["RW23",34.79237,-81.18609,241.0,4998.0],["RW35",34.78352,-81.19694,354.0,5000.0]],"procs":[{"id":"JOOLS3","type":"STAR","trans":[{"t":"THRSR","k":"enroute","legs":[["THRSR",33.62924,-84.4351,"IF",null,null,null,null,null,null,null,null,0,null,null,null,null],["PENFI",33.74611,-83.25171,"TF",null,null,null,null,null,null,null,null,0,null,null,null,null],["HRTWL",34.25148,-82.15432,"TF",null,null,null,null,null,null,null,null,0,null,null,null,null],["ZELLE",34.35911,-81.93254,"TF",null,null,null,null,null,null,null,null,0,null,null,null,null],["JOOLS",34.50945,-81.62037,"TF",null,null,null,null,null,null,null,null,0,null,null,null,null]]},{"t":"WANSA","k":"enroute","legs":[["WANSA",33.70725,-82.16222,"IF",null,null,null,null,null,null,null,null,0,null,null,null,null],["JEENI",33.83937,-82.16059,"TF",null,null,null,null,null,null,null,null,0,null,null,null,null],["HRTWL",34.25148,-82.15432,"TF",null,null,null,null,null,null,null,null,0,null,null,null,null],["ZELLE",34.35911,-81.93254,"TF",null,null,null,null,null,null,null,null,0,null,null,null,null],["JOOLS",34.50945,-81.62037,"TF",null,null,null,null,null,null,null,null,0,null,null,null,null]]},{"t":"ALL","k":"common","legs":[["JOOLS",34.50945,-81.62037,"IF",null,null,null,null,null,null,null,null,0,null,null,null,null],["CHPTR",34.59299,-81.44567,"TF",null,null,null,null,null,null,null,null,0,null,null,null,null],["KEGGG",34.62634,-81.3757,"TF",null,"+",4000,null,null,null,null,null,2,null,null,null,null],["KEGGG",34.62634,-81.3757,"FM",null,null,null,null,null,70.0,null,null,0,["ILM",34.35165,-77.87438],283.4,174.4,null]]}]},{"id":"LIINN3","type":"STAR","trans":[{"t":"HMV","k":"enroute","legs":[["HMV",36.43706,-82.1296,"IF",null,null,null,null,null,null,null,null,0,null,null,null,null],["LOOIE",35.76114,-81.94305,"TF",null,null,null,null,null,null,null,null,0,null,null,null,null],["JALIT",35.55987,-81.88813,"TF",null,null,null,null,null,null,null,null,0,null,null,null,null]]},{"t":"SOT","k":"enroute","legs":[["SOT",35.7901,-83.05237,"IF",null,null,null,null,null,null,null,null,0,null,null,null,null],["WUUTN",35.62218,-82.1968,"TF",null,null,null,null,null,null,null,null,0,null,null,null,null],["JALIT",35.55987,-81.88813,"TF",null,null,null,null,null,null,null,null,0,null,null,null,null]]},{"t":"VXV","k":"enroute","legs":[["VXV",35.90484,-83.89472,"IF",null,null,null,null,null,null,null,null,0,null,null,null,null],["CLRRY",35.67431,-82.18365,"TF",null,null,null,null,null,null,null,null,0,null,null,null,null],["JALIT",35.55987,-81.88813,"TF",null,null,null,null,null,null,null,null,0,null,null,null,null]]},{"t":"ALL","k":"common","legs":[["JALIT",35.55987,-81.88813,"IF",null,null,null,null,null,null,null,null,0,null,null,null,null],["LIINN",35.48798,-81.70385,"TF",null,null,null,null,null,null,null,null,0,null,null,null,null],["CLT",35.19029,-80.95175,"TF",null,null,null,null,null,null,null,null,0,null,null,null,null]]}]},{"id":"MAJIC4","type":"STAR","trans":[{"t":"LIB","k":"enroute","legs":[["LIB",35.81162,-79.61259,"IF",null,null,null,null,null,null,null,null,0,null,null,null,null],["MAJIC",35.81191,-80.43611,"TF",null,null,null,null,null,null,null,null,0,null,null,null,null]]},{"t":"LYH","k":"enroute","legs":[["LYH",37.25458,-79.23638,"IF",null,null,null,null,null,null,null,null,0,null,null,null,null],["KELLS",36.58616,-79.78617,"TF",null,null,null,null,null,null,null,null,0,null,null,null,null],["MAYOS",36.32657,-79.99647,"TF",null,null,null,null,null,null,null,null,0,null,null,null,null],["MAJIC",35.81191,-80.43611,"TF",null,null,null,null,null,null,null,null,0,null,null,null,null]]},{"t":"RW05","k":"runway","legs":[["MAJIC",35.81191,-80.43611,"IF",null,null,null,null,null,null,null,null,0,null,null,null,null],["SUDSY",35.74296,-80.49379,"TF",null,null,null,null,null,null,null,null,0,null,null,null,null],["GIZMO",35.54975,-80.65479,"TF",null,null,null,null,null,null,null,null,0,null,null,null,null],["CLT",35.19029,-80.95175,"TF",null,null,null,null,null,null,null,null,0,null,null,null,null]]},{"t":"RW17","k":"runway","legs":[["MAJIC",35.81191,-80.43611,"IF",null,null,null,null,null,null,null,null,0,null,null,null,null],["SUDSY",35.74296,-80.49379,"TF",null,null,null,null,null,null,null,null,0,null,null,null,null],["GIZMO",35.54975,-80.65479,"TF",null,null,null,null,null,null,null,null,0,null,null,null,null]]},{"t":"RW23","k":"runway","legs":[["MAJIC",35.81191,-80.43611,"IF",null,null,null,null,null,null,null,null,0,null,null,null,null],["SUDSY",35.74296,-80.49379,"TF",null,null,null,null,null,null,null,null,0,null,null,null,null],["GIZMO",35.54975,-80.65479,"TF",null,null,null,null,null,null,null,null,0,null,null,null,null]]},{"t":"RW35","k":"runway","legs":[["MAJIC",35.81191,-80.43611,"IF",null,null,null,null,null,null,null,null,0,null,null,null,null],["SUDSY",35.74296,-80.49379,"TF",null,null,null,null,null,null,null,null,0,null,null,null,null],["GIZMO",35.54975,-80.65479,"TF",null,null,null,null,null,null,null,null,0,null,null,null,null],["CLT",35.19029,-80.95175,"TF",null,null,null,null,null,null,null,null,0,null,null,null,null]]}]},{"id":"RASLN3","type":"STAR","trans":[{"t":"FLO","k":"enroute","legs":[["FLO",34.23297,-79.65716,"IF",null,null,null,null,null,null,null,null,0,null,null,null,null],["DSTEE",34.51534,-79.96593,"TF",null,null,null,null,null,null,null,null,0,null,null,null,null],["RODEZ",34.64395,-80.10755,"TF",null,null,null,null,null,null,null,null,0,null,null,null,null],["RASLN",34.80646,-80.28739,"TF",null,null,null,null,null,null,null,null,0,null,null,null,null]]},{"t":"ALL","k":"common","legs":[["RASLN",34.80646,-80.28739,"IF",null,null,null,null,null,null,null,null,0,null,null,null,null],["CLT",35.19029,-80.95175,"TF",null,"+",3000,null,null,null,null,null,0,null,null,null,null]]}]},{"id":"R17","type":"APP","trans":[{"t":"CIBOB","k":"transition","legs":[["CIBOB",34.99038,-80.96729,"IF",null,null,null,null,null,null,null,null,0,null,null,null,null],["HUPNI",35.0008,-81.10771,"TF",null,"+",3000,null,null,null,null,null,0,null,null,null,null],["SUNYO",34.9766,-81.24663,"TF",null,"+",3000,null,null,null,null,null,0,null,null,null,null]]},{"t":"SUNYO","k":"transition","legs":[["SUNYO",34.9766,-81.24663,"HF","R","+",3000,null,null,174.0,4.0,null,0,null,null,null,null]]},{"t":"(final)","k":"final","legs":[["SUNYO",34.9766,-81.24663,"IF",null,"+",3000,null,null,null,null,null,0,null,null,null,null],["IYDAD",34.87837,-81.22132,"TF",null,"+",2300,null,null,null,null,null,0,null,null,null,[34.79696,-81.20039]],["CIXUV",34.83779,-81.21088,"TF",null,"V",1480,1497,null,null,null,-3.04,0,null,null,null,null],["RW17",34.79696,-81.20039,"TF",null,null,691,null,null,null,null,-3.04,2,null,null,null,null],[null,null,null,"CA",null,"+",907,null,null,174.0,null,null,1,null,null,null,null],["HUSNY",34.60386,-81.15092,"DF",null,"+",3000,null,null,null,null,null,2,null,null,null,null],["HUSNY",34.60386,-81.15092,"HM","R","+",3000,null,null,354.1,4.0,null,0,null,null,null,null]]}],"name":"RNAV (GPS) RWY 17"},{"id":"R35","type":"APP","trans":[{"t":"GREAT","k":"transition","legs":[["GREAT",34.4571,-81.0083,"IF",null,null,null,null,null,null,null,null,0,null,null,null,null],["HUSNY",34.60386,-81.15092,"TF",null,"+",3000,null,null,null,null,null,0,null,null,null,null]]},{"t":"HUSNY","k":"transition","legs":[["HUSNY",34.60386,-81.15092,"HF","R","+",3000,null,null,354.1,4.0,null,0,null,null,null,null]]},{"t":"TAYSO","k":"transition","legs":[["TAYSO",34.575,-81.31547,"IF",null,null,null,null,null,null,null,null,0,null,null,null,null],["HUSNY",34.60386,-81.15092,"TF",null,"+",3000,null,null,null,null,null,0,null,null,null,null]]},{"t":"(final)","k":"final","legs":[["HUSNY",34.60386,-81.15092,"IF",null,"+",3000,null,null,null,null,null,0,null,null,null,null],["FETBY",34.70713,-81.17735,"TF",null,"+",2200,null,null,null,null,null,0,null,null,null,[34.78352,-81.19694]],["HETEB",34.74596,-81.18731,"TF",null,"V",1420,1429,null,null,null,-3.0,0,null,null,null,null],["RW35",34.78352,-81.19694,"TF",null,null,691,null,null,null,null,-3.0,2,null,null,null,null],[null,null,null,"CA",null,"+",940,null,null,354.1,null,null,1,null,null,null,null],["SUNYO",34.9766,-81.24663,"DF",null,"+",3000,null,null,null,null,null,2,null,null,null,null],["SUNYO",34.9766,-81.24663,"HM","R","+",3000,null,null,174.0,4.0,null,0,null,null,null,null]]}],"name":"RNAV (GPS) RWY 35"}]}