{"id":"KDTA","name":"Delta Muni","lat":39.38283,"lon":-112.50221,"elev":4760.0,"mv":11.0,"rw":[["RW17",39.39115,-112.50216,169.0,6065.0],["RW35",39.37451,-112.50226,349.0,6065.0]],"procs":[{"id":"DTA1","type":"SID","trans":[{"t":"RW17","k":"runway","legs":[["DTA",39.30226,-112.50556,"CF",null,null,null,null,null,167.0,4.4,null,0,["DTA",39.30226,-112.50556],0.0,0.0,null]]},{"t":"RW35","k":"runway","legs":[[null,null,null,"VA",null,"+",5800,null,null,349.3,null,null,0,null,null,null,null],[null,null,null,"VI","L",null,null,null,null,180.0,null,null,0,null,null,null,null],["DTA",39.30226,-112.50556,"CF",null,null,null,null,null,130.0,7.0,null,0,["DTA",39.30226,-112.50556],0.0,0.0,null]]}]},{"id":"D17","type":"APP","trans":[{"t":"DTA","k":"transition","legs":[["DTA",39.30226,-112.50556,"IF",null,null,null,null,null,null,null,null,0,null,null,null,null],["GIDEY",39.60244,-112.49404,"TF",null,"+",9100,null,null,null,null,null,0,null,null,null,null],["GIDEY",39.60244,-112.49404,"PI","L","+",9100,null,null,30.7,10.0,null,0,["DTA",39.30226,-112.50556],345.7,18.0,null]]},{"t":"LOLIC","k":"transition","legs":[["LOLIC",39.71832,-112.46789,"IF",null,null,null,null,null,null,null,null,0,null,null,null,null],["ZUVEM",39.68173,-112.49098,"TF",null,"+",7600,null,null,null,null,null,0,null,null,null,null],["GIDEY",39.60244,-112.49404,"TF",null,"+",7600,null,null,null,null,null,0,null,null,null,null]]},{"t":"RUBOY","k":"transition","legs":[["RUBOY",39.5766,-112.34799,"IF",null,null,null,null,null,null,null,null,0,null,null,null,null],["GIDEY",39.60244,-112.49404,"AF","L","+",7600,null,null,8.0,null,null,0,["DTA",39.30226,-112.50556],345.7,18.0,null]]},{"t":"(final)","k":"final","legs":[["GIDEY",39.60244,-112.49404,"IF",null,"+",7600,null,null,null,null,null,0,["DTA",39.30226,-112.50556],345.7,18.0,null],["EACKS",39.48023,-112.49874,"CF",null,"+",6500,null,null,165.7,7.3,null,0,["DTA",39.30226,-112.50556],345.7,10.7,[39.30226,-112.50556]],["RW17",39.39115,-112.50216,"CF",null,null,4799,null,null,165.7,5.3,-3.0,2,["DTA",39.30226,-112.50556],345.7,5.3,null],["DUDTE",39.21895,-112.50874,"CF",null,null,null,null,null,165.7,10.3,null,1,["DTA",39.30226,-112.50556],165.7,5.0,null],["DTA",39.30226,-112.50556,"CF","R","+",9600,null,null,24.0,5.0,null,2,["DTA",39.30226,-112.50556],0.0,0.0,null],["DTA",39.30226,-112.50556,"HM","L","+",9600,null,null,4.0,null,null,0,null,null,null,null]]}],"name":"VOR/DME RWY 17"},{"id":"R17","type":"APP","trans":[{"t":"AADCO","k":"transition","legs":[["AADCO",39.78482,-112.46183,"IF",null,null,null,null,null,null,null,null,0,null,null,null,null],["WUNDI",39.65671,-112.50054,"TF",null,"+",9700,null,null,null,null,null,0,null,null,null,null]]},{"t":"DTA","k":"transition","legs":[["DTA",39.30226,-112.50556,"IF",null,null,null,null,null,null,null,null,0,null,null,null,null],["WUNDI",39.65671,-112.50054,"TF",null,"+",9700,null,null,null,null,null,2,null,null,null,null],["WUNDI",39.65671,-112.50054,"HF","L","+",9700,null,null,186.0,7.0,null,0,null,null,null,null]]},{"t":"PUCIT","k":"transition","legs":[["PUCIT",39.6832,-112.28638,"IF",null,null,null,null,null,null,null,null,0,null,null,null,null],["WUNDI",39.65671,-112.50054,"TF",null,"+",9700,null,null,null,null,null,0,null,null,null,null]]},{"t":"(final)","k":"final","legs":[["WUNDI",39.65671,-112.50054,"IF",null,"+",9700,null,null,null,null,null,0,null,null,null,null],["LUSSI",39.48501,-112.50161,"TF",null,"+",6600,null,null,null,null,null,0,null,null,null,[39.39115,-112.50216]],["ZOBMA",39.4145,-112.50202,"TF",null,"V",5240,5254,null,null,null,-3.0,0,null,null,null,null],["RW17",39.39115,-112.50216,"TF",null,null,4808,null,null,null,null,-3.0,2,null,null,null,null],[null,null,null,"CA",null,"+",5300,null,null,169.3,null,null,1,null,null,null,null],["JULIK",39.15301,-112.52571,"DF","R","+",12000,null,null,null,null,null,2,null,null,null,null],["JULIK",39.15301,-112.52571,"HM","R","+",12000,null,null,176.0,7.0,null,0,null,null,null,null]]}],"name":"RNAV (GPS) RWY 17"},{"id":"R35","type":"APP","trans":[{"t":"BICAN","k":"transition","legs":[["BICAN",38.9705,-112.55023,"IF",null,null,null,null,null,null,null,null,0,null,null,null,null],["UTONE",39.18555,-112.50341,"TF",null,"+",7300,null,null,null,null,null,0,null,null,null,null]]},{"t":"RUBOY","k":"transition","legs":[["RUBOY",39.5766,-112.34799,"IF",null,null,null,null,null,null,null,null,0,null,null,null,null],["UTONE",39.18555,-112.50341,"TF",null,"+",7300,null,null,null,null,null,2,null,null,null,null],["UTONE",39.18555,-112.50341,"HF","R","+",7300,null,null,349.3,7.0,null,0,null,null,null,null]]},{"t":"WADOK","k":"transition","legs":[["WADOK",39.55192,-112.48301,"IF",null,null,null,null,null,null,null,null,0,null,null,null,null],["UTONE",39.18555,-112.50341,"TF",null,"+",7300,null,null,null,null,null,2,null,null,null,null],["UTONE",39.18555,-112.50341,"HF","R","+",7300,null,null,349.3,7.0,null,0,null,null,null,null]]},{"t":"ZIBRA","k":"transition","legs":[["ZIBRA",38.99513,-112.67275,"IF",null,null,null,null,null,null,null,null,0,null,null,null,null],["UTONE",39.18555,-112.50341,"TF",null,"+",7300,null,null,null,null,null,0,null,null,null,null]]},{"t":"(final)","k":"final","legs":[["UTONE",39.18555,-112.50341,"IF",null,"+",7300,null,null,null,null,null,0,null,null,null,null],["TAVTE",39.29565,-112.50272,"TF",null,"+",6300,null,null,null,null,null,0,null,null,null,[39.37451,-112.50226]],["RW35",39.37451,-112.50226,"TF",null,null,4794,null,null,null,null,-3.0,2,null,null,null,null],[null,null,null,"CA",null,"+",4955,null,null,349.3,null,null,1,null,null,null,null],["HADUS",39.56105,-112.50116,"DF",null,null,null,null,null,null,null,null,0,null,null,null,null],["PUCIT",39.6832,-112.28638,"TF",null,"+",10300,null,null,null,null,null,2,null,null,null,null],["PUCIT",39.6832,-112.28638,"HM","R","+",10300,null,null,193.1,7.0,null,0,null,null,null,null]]}],"name":"RNAV (GPS) RWY 35"},{"id":"S35","type":"APP","trans":[{"t":"BICAN","k":"transition","legs":[["BICAN",38.9705,-112.55023,"IF",null,null,null,null,null,null,null,null,0,null,null,null,null],["JULIK",39.15301,-112.52571,"TF",null,"+",7900,null,null,null,null,null,0,null,null,null,null],["DELKE",39.16412,-112.58097,"AF","R","+",7300,null,null,170.0,null,null,0,["DTA",39.30226,-112.50556],187.0,9.0,null]]},{"t":"DTA","k":"transition","legs":[["DTA",39.30226,-112.50556,"PI","L","+",7300,null,null,232.0,10.0,null,0,["DTA",39.30226,-112.50556],0.0,0.0,null]]},{"t":"ZIBRA","k":"transition","legs":[["ZIBRA",38.99513,-112.67275,"IF",null,null,null,null,null,null,null,null,0,null,null,null,null],["DELKE",39.16412,-112.58097,"CF",null,"+",7300,null,null,7.0,11.0,null,0,["DTA",39.30226,-112.50556],187.0,9.0,null]]},{"t":"(final)","k":"final","legs":[["DELKE",39.16412,-112.58097,"IF",null,"+",7300,null,null,null,null,null,0,["DTA",39.30226,-112.50556],187.0,9.0,null],["DTA",39.30226,-112.50556,"CF",null,"+",6200,null,null,7.0,9.0,null,0,["DTA",39.30226,-112.50556],0.0,0.0,[39.30226,-112.50556]],["RW35",39.37451,-112.50226,"CF",null,null,4787,null,null,346.0,4.3,-3.07,2,["DTA",39.30226,-112.50556],346.0,4.3,null],[null,null,null,"CA",null,"+",5800,null,null,346.0,null,null,1,null,null,null,null],["DTA",39.30226,-112.50556,"DF","R","+",9600,null,null,null,null,null,2,null,null,null,null],["DTA",39.30226,-112.50556,"HM","L","+",9600,null,null,4.0,null,null,0,null,null,null,null]]}],"name":"VOR/DME RWY 35"}]}