{"id":"KMXA","name":"Manila Muni","lat":35.89445,"lon":-90.15457,"elev":243.0,"mv":-1.0,"rw":[["RW18",35.90022,-90.15454,181.0,4201.0],["RW36",35.88884,-90.15461,1.0,4201.0]],"procs":[{"id":"R18","type":"APP","trans":[{"t":"BLITH","k":"transition","legs":[["BLITH",36.06815,-90.15349,"HF","R","+",2800,null,null,181.3,4.0,null,0,null,null,null,null]]},{"t":"(final)","k":"final","legs":[["BLITH",36.06815,-90.15349,"IF",null,"+",2800,null,null,null,null,null,0,null,null,null,null],["HATOP",35.97986,-90.15404,"TF",null,"+",1800,null,null,null,null,null,0,null,null,null,null],["JITRU",35.92692,-90.15437,"TF",null,"+",780,null,null,null,null,null,0,null,null,null,null],["RW18",35.90022,-90.15454,"TF",null,null,281,null,null,null,null,0.0,2,null,null,null,null],[null,null,null,"CA",null,"+",640,null,null,181.3,null,null,1,null,null,null,null],["DUNLE",35.72179,-90.15565,"DF",null,"+",2600,null,null,null,null,null,2,null,null,null,null],["DUNLE",35.72179,-90.15565,"HM","R","+",2600,null,null,1.3,4.0,null,0,null,null,null,null]]}],"name":"RNAV (GPS) RWY 18"},{"id":"R36","type":"APP","trans":[{"t":"DUNLE","k":"transition","legs":[["DUNLE",35.72179,-90.15565,"HF","R","+",2600,null,null,1.3,4.0,null,0,null,null,null,null]]},{"t":"(final)","k":"final","legs":[["DUNLE",35.72179,-90.15565,"IF",null,"+",2600,null,null,null,null,null,0,null,null,null,null],["JISEP",35.80959,-90.15509,"TF",null,"+",2300,null,null,null,null,null,0,null,null,null,null],["JAPAB",35.86459,-90.15476,"TF",null,"V",900,900,null,null,null,-4.0,0,null,null,null,null],["RW36",35.88884,-90.15461,"TF",null,null,283,null,null,null,null,-4.0,2,null,null,null,null],[null,null,null,"CA",null,"+",552,null,null,1.3,null,null,1,null,null,null,null],["BLITH",36.06815,-90.15349,"DF",null,"+",2800,null,null,null,null,null,2,null,null,null,null],["BLITH",36.06815,-90.15349,"HM","R","+",2800,null,null,181.3,4.0,null,0,null,null,null,null]]}],"name":"RNAV (GPS) RWY 36"}]}