{"id":"KWMC","name":"Winnemucca Muni","lat":40.89661,"lon":-117.80589,"elev":4308.0,"mv":16.0,"rw":[["RW02",40.89097,-117.80614,24.0,4800.0],["RW14",40.906,-117.81395,144.0,7000.0],["RW20",40.90112,-117.79507,204.0,4800.0],["RW32",40.888,-117.80512,324.0,7000.0]],"procs":[{"id":"FESKO1","type":"SID","trans":[{"t":"RW02","k":"runway","legs":[[null,null,null,"VA",null,"+",5600,null,null,23.6,null,null,0,null,null,null,[40.89661,-117.80589]],["FESKO",40.50866,-117.64808,"DF","L","+",11000,null,null,null,null,null,0,null,null,null,null]]},{"t":"RW14","k":"runway","legs":[[null,null,null,"VA",null,"+",4900,null,null,143.6,null,null,0,null,null,null,null],["FESKO",40.50866,-117.64808,"DF",null,"+",11000,null,null,null,null,null,0,null,null,null,null]]},{"t":"RW20","k":"runway","legs":[[null,null,null,"VI",null,null,null,null,null,203.6,null,null,0,null,null,null,null],["FESKO",40.50866,-117.64808,"CF",null,"+",11000,null,null,144.5,23.5,null,0,["FMG",39.53128,-119.65608],41.0,109.5,null]]},{"t":"RW32","k":"runway","legs":[[null,null,null,"VA",null,"+",5700,null,null,323.6,null,null,0,null,null,null,null],["FESKO",40.50866,-117.64808,"DF","L","+",11000,null,null,null,null,null,0,null,null,null,null]]}]},{"id":"R14","type":"APP","trans":[{"t":"GOWZE","k":"transition","legs":[["GOWZE",41.13884,-118.27346,"IF",null,null,null,null,null,null,null,null,0,null,null,null,null],["TOWOD",41.09438,-117.90662,"TF",null,"+",7400,null,null,null,null,null,0,null,null,null,null]]},{"t":"SDO","k":"transition","legs":[["SDO",41.40706,-118.03472,"IF",null,null,null,null,null,null,null,null,0,null,null,null,null],["LOKKA",41.26636,-117.99172,"TF",null,"+",8700,null,null,null,null,null,0,null,null,null,null],["BOZJE",41.17257,-117.94525,"TF",null,"+",7700,null,null,null,null,null,0,null,null,null,null],["TOWOD",41.09438,-117.90662,"TF",null,"+",7400,null,null,null,null,null,0,null,null,null,null]]},{"t":"(final)","k":"final","legs":[["TOWOD",41.09438,-117.90662,"IF",null,"+",7400,null,null,null,null,null,0,null,null,null,null],["WINQY",41.00048,-117.86035,"TF",null,"+",6300,null,null,null,null,null,0,null,null,null,[40.906,-117.81395]],["RW14",40.906,-117.81395,"TF",null,null,4341,null,null,null,null,-3.0,2,null,null,null,null],[null,null,null,"CA",null,"+",4708,null,null,143.6,null,null,1,null,null,null,null],["MUXSU",40.87787,-117.80015,"DF",null,null,null,null,null,null,null,null,0,null,null,null,null],["CUTVA",40.39088,-117.59994,"TF",null,"+",12000,null,null,null,null,null,2,null,null,null,null],["CUTVA",40.39088,-117.59994,"HM","R","+",12000,null,null,238.0,7.0,null,0,null,null,null,null]]}],"name":"RNAV (GPS) RWY 14"},{"id":"R32","type":"APP","trans":[{"t":"FESKO","k":"transition","legs":[["FESKO",40.50866,-117.64808,"IF",null,null,null,null,null,null,null,null,0,null,null,null,null],["BUNFI",40.60631,-117.68126,"TF",null,"+",9100,null,null,null,null,null,0,null,null,null,null],["DUGDE",40.69993,-117.71319,"TF",null,"+",7200,null,null,null,null,null,0,null,null,null,null]]},{"t":"(final)","k":"final","legs":[["DUGDE",40.69993,-117.71319,"IF",null,"+",7200,null,null,null,null,null,0,null,null,null,null],["PUHGI",40.79384,-117.75902,"TF",null,"+",6300,null,null,null,null,null,0,null,null,null,[40.888,-117.80512]],["RW32",40.888,-117.80512,"TF",null,null,4348,null,null,null,null,-3.0,2,null,null,null,null],[null,null,null,"CA",null,"+",4708,null,null,323.6,null,null,1,null,null,null,null],["EXATY",40.91926,-117.82045,"DF",null,null,null,null,null,null,null,null,0,null,null,null,null],["SDO",41.40706,-118.03472,"TF",null,"+",10000,null,null,null,null,null,2,null,null,null,null],["SDO",41.40706,-118.03472,"HM","R","+",10000,null,null,16.9,7.0,null,0,null,null,null,null]]}],"name":"RNAV (GPS) RWY 32"}]}