{"id":"M53","name":"Humboldt Muni","lat":35.80218,"lon":-88.87493,"elev":421.0,"mv":-2.0,"rw":[["RW04",35.79826,-88.87966,46.0,4003.0],["RW22",35.80611,-88.87021,226.0,4003.0]],"procs":[{"id":"R04","type":"APP","trans":[{"t":"CAVTO","k":"transition","legs":[["CAVTO",35.66351,-89.04123,"HF","R","+",3000,null,null,46.3,4.0,null,0,null,null,null,null]]},{"t":"(final)","k":"final","legs":[["CAVTO",35.66351,-89.04123,"IF",null,"+",3000,null,null,null,null,null,0,null,null,null,null],["FELIV",35.73633,-88.954,"TF",null,"+",2100,null,null,null,null,null,0,null,null,null,null],["XEFVI",35.76605,-88.91835,"TF",null,"+",1300,null,null,null,null,null,0,null,null,null,null],["RW04",35.79826,-88.87966,"TF",null,null,447,null,null,null,null,0.0,2,null,null,null,null],[null,null,null,"CA",null,"+",780,null,null,46.4,null,null,1,null,null,null,null],["FASKA",35.93966,-88.7092,"DF",null,"+",3000,null,null,null,null,null,2,null,null,null,null],["FASKA",35.93966,-88.7092,"HM","R","+",3000,null,null,226.5,4.0,null,0,null,null,null,null]]}],"name":"RNAV (GPS) RWY 4"},{"id":"R22","type":"APP","trans":[{"t":"FASKA","k":"transition","legs":[["FASKA",35.93966,-88.7092,"HF","R","+",3000,null,null,226.5,4.0,null,0,null,null,null,null]]},{"t":"(final)","k":"final","legs":[["FASKA",35.93966,-88.7092,"IF",null,"+",3000,null,null,null,null,null,0,null,null,null,null],["WOKMU",35.86704,-88.79686,"TF",null,"+",2100,null,null,null,null,null,0,null,null,null,null],["XITRY",35.83711,-88.83291,"TF",null,"V",1300,1300,null,null,null,-3.0,0,null,null,null,null],["RW22",35.80611,-88.87021,"TF",null,null,472,null,null,null,null,-3.0,2,null,null,null,null],[null,null,null,"CA",null,"+",821,null,null,226.5,null,null,1,null,null,null,null],["CAVTO",35.66351,-89.04123,"DF",null,"+",3000,null,null,null,null,null,2,null,null,null,null],["CAVTO",35.66351,-89.04123,"HM","R","+",3000,null,null,46.3,4.0,null,0,null,null,null,null]]}],"name":"RNAV (GPS) RWY 22"}]}